[
  {
    "code": "EDU 201",
    "title": "Foundations of Learning",
    "level": "undergraduate",
    "term": "Fall 2024",
    "description": "Principles of learning science; inclusive course design; formative assessment.",
    "syllabus_url": "#"
  },
  {
    "code": "EDU 510",
    "title": "Teaching in Higher Ed",
    "level": "graduate",
    "term": "Spring 2025",
    "description": "Evidence-based pedagogy, student motivation, and reflective practice.",
    "syllabus_url": "#"
  },
  {
    "code": "DIGH 320",
    "title": "Digital Humanities Studio",
    "level": "undergraduate",
    "term": "Spring 2024",
    "description": "Project-based exploration of digital methods for humanities research.",
    "syllabus_url": "#"
  }
]